{
    "calcinfo_nalpha": 5,
    "calcinfo_natom": 2,
    "calcinfo_nbeta": 5,
    "calcinfo_nmo": 10,
    "molecule": {
        "geometry": [
            [
                0.0,
                0.0,
                0.20200001570223414
            ],
            [
                0.0,
                0.0,
                -1.6160001256178735
            ]
        ],
        "symbols": [
            "O",
            "H"
        ]
    },
    "parameters": {
        "charge": -1.0,
        "conv_only_dens": false,
        "dconv": 0.0001,
        "derivatives": false,
        "dipole": false,
        "econv": 1e-05,
        "ginitial_hessian": false,
        "gmaxiter": 20,
        "gopt": false,
        "gprec": 0.0001,
        "gtest": false,
        "gtol": 0.0001,
        "gval": 1e-05,
        "k": -1,
        "l": 51.616,
        "lo": 0.001329,
        "loadbalparts": 2,
        "maxiter": 25,
        "maxrotn": 0.25,
        "maxsub": 10,
        "nalpha": 5,
        "nbeta": 5,
        "nio": 1,
        "nmo_alpha": 5,
        "nmo_beta": 5,
        "no_compute": false,
        "noiter": false,
        "nopen": 0,
        "npt_plot": 101,
        "nv_factor": 1,
        "nvalpha": 0,
        "nvbeta": 0,
        "orbitalshift": 0.0,
        "plot_cell": [],
        "plotcoul": false,
        "plotdens": false,
        "plothi": -1,
        "plotlo": 0,
        "print_level": 3,
        "protocol": [
            0.0001,
            1e-06
        ],
        "psp_calc": false,
        "pure_ae": true,
        "restart": false,
        "restartao": false,
        "save": true,
        "smear": 0.0,
        "spin_restricted": true,
        "vnucextra": 2
    },
    "precision": {
        "dconv": 0.0001,
        "econv": 1e-05,
        "eprec": 0.0001,
        "k": 8,
        "thresh": 1e-06
    },
    "return_energy": -75.76447373690898,
    "scf_e_data": {
        "e_coulomb": [
            50.126612391905816,
            44.42980927506002,
            44.830033913280886,
            45.309381210496,
            44.68142677905418,
            44.9883170881788,
            44.91829884450958,
            44.898371682286026,
            44.303131617288145,
            44.751787171490946,
            44.81534455315665,
            44.74114688068383,
            44.72219055500737,
            44.79963792134082,
            44.738127511005125,
            44.71731901048233,
            44.84292371861779,
            44.738808980301386,
            44.698981793833866,
            44.99608543541666,
            44.62043089762426,
            44.082456369951906,
            44.80487252443461,
            44.5146202242421,
            44.178892102064715,
            44.178841687368596,
            46.607437515981495,
            44.22379414061106,
            44.95354506558649,
            44.871248647329324,
            44.85914806281133,
            45.06336690109137,
            44.932027949986235,
            45.172024835482176,
            44.67409361550007,
            45.02649699580371,
            45.08640803583786,
            45.041758216755376,
            44.94950581111244,
            44.9940216598199,
            45.3117998306748,
            44.97473459513971,
            45.06436015101087,
            44.92425511523566,
            45.02664491022646,
            45.063270612431026,
            45.055481378915204,
            44.831505234125196,
            44.802256638131205,
            44.85847132884123
        ],
        "e_kinetic": [
            78.5008534436703,
            74.33147442132221,
            75.16608769217353,
            75.61526609552479,
            75.6080833271257,
            75.49392418293894,
            75.49996602913298,
            75.37392105865531,
            75.27902407387626,
            75.46304016828464,
            75.4830590752196,
            75.44970173864415,
            75.44122657859009,
            75.48326244698674,
            75.44324636365538,
            75.45907017555183,
            75.49762836584833,
            75.45280935865722,
            75.43679125226576,
            75.59668546984123,
            75.423988870371,
            75.26158444783887,
            75.51046011781082,
            75.37335970387055,
            75.29232295497677,
            75.29241357342643,
            76.49334324539618,
            75.08151524222438,
            75.57956370172903,
            75.34174258873654,
            75.53609000884606,
            75.57420263663863,
            75.56293614701178,
            75.58597633824023,
            75.48125629429066,
            75.43614225870014,
            75.50081189076971,
            75.59658915967124,
            75.50177306115222,
            75.53988278792508,
            75.7402127848997,
            75.54921162601677,
            75.56114376326353,
            75.52368202985133,
            75.58347055605634,
            75.61764038557817,
            75.58581680966148,
            75.48811103576611,
            75.47265277492885,
            75.49406027435576
        ],
        "e_local": [
            0.0,
            0.0,
            0.0,
            0.0,
            0.0,
            0.0,
            0.0,
            0.0,
            0.0,
            0.0,
            0.0,
            0.0,
            0.0,
            0.0,
            0.0,
            0.0,
            0.0,
            0.0,
            0.0,
            0.0,
            0.0,
            0.0,
            0.0,
            0.0,
            0.0,
            0.0,
            0.0,
            0.0,
            0.0,
            0.0,
            0.0,
            0.0,
            0.0,
            0.0,
            0.0,
            0.0,
            0.0,
            0.0,
            0.0,
            0.0,
            0.0,
            0.0,
            0.0,
            0.0,
            0.0,
            0.0,
            0.0,
            0.0,
            0.0,
            0.0
        ],
        "e_nrep": [
            4.400439701941357,
            4.400439701941357,
            4.400439701941357,
            4.400439701941357,
            4.400439701941357,
            4.400439701941357,
            4.400439701941357,
            4.400439701941357,
            4.400439701941357,
            4.400439701941357,
            4.400439701941357,
            4.400439701941357,
            4.400439701941357,
            4.400439701941357,
            4.400439701941357,
            4.400439701941357,
            4.400439701941357,
            4.400439701941357,
            4.400439701941357,
            4.400439701941357,
            4.400439701941357,
            4.400439701941357,
            4.400439701941357,
            4.400439701941357,
            4.400439701941357,
            4.400439701941357,
            4.400439701941357,
            4.400439701941357,
            4.400439701941357,
            4.400439701941357,
            4.400439701941357,
            4.400439701941357,
            4.400439701941357,
            4.400439701941357,
            4.400439701941357,
            4.400439701941357,
            4.400439701941357,
            4.400439701941357,
            4.400439701941357,
            4.400439701941357,
            4.400439701941357,
            4.400439701941357,
            4.400439701941357,
            4.400439701941357,
            4.400439701941357,
            4.400439701941357,
            4.400439701941357,
            4.400439701941357,
            4.400439701941357,
            4.400439701941357
        ],
        "e_nuclear": [
            -198.7912314757713,
            -189.91950017577855,
            -191.1587602615703,
            -192.0328547520961,
            -191.45910443279521,
            -191.62967051971413,
            -191.57229581078798,
            -191.43131047873118,
            -190.79761640989508,
            -191.38559364867865,
            -191.46248696600367,
            -191.36318536496526,
            -191.33788070725697,
            -191.448389493232,
            -191.35442774903723,
            -191.35027997783163,
            -191.50160977734305,
            -191.36392605404689,
            -191.3123485914465,
            -191.73442556912332,
            -191.2275099795082,
            -190.5776062472354,
            -191.47849622721375,
            -191.08224222628866,
            -190.69664965373616,
            -190.6966541883768,
            -194.02245573677362,
            -190.5358759469666,
            -191.67688591694508,
            -191.37520444377841,
            -191.55214273837487,
            -191.7734171807623,
            -191.64334076459386,
            -191.88290872055182,
            -191.33191200865173,
            -191.60714542352514,
            -191.72390810778631,
            -191.77582427767322,
            -191.60278261514003,
            -191.67956708380626,
            -192.15715002110716,
            -191.66998238264358,
            -191.76319511251933,
            -191.6003993838383,
            -191.74989354491987,
            -191.81568959091197,
            -191.77905590706888,
            -191.4823158276485,
            -191.44092897544814,
            -191.51237807959365
        ],
        "e_pcm": [
            0.0,
            0.0,
            0.0,
            0.0,
            0.0,
            0.0,
            0.0,
            0.0,
            0.0,
            0.0,
            0.0,
            0.0,
            0.0,
            0.0,
            0.0,
            0.0,
            0.0,
            0.0,
            0.0,
            0.0,
            0.0,
            0.0,
            0.0,
            0.0,
            0.0,
            0.0,
            0.0,
            0.0,
            0.0,
            0.0,
            0.0,
            0.0,
            0.0,
            0.0,
            0.0,
            0.0,
            0.0,
            0.0,
            0.0,
            0.0,
            0.0,
            0.0,
            0.0,
            0.0,
            0.0,
            0.0,
            0.0,
            0.0,
            0.0,
            0.0
        ],
        "e_tot": [
            -75.40231055887436,
            -75.67309418698599,
            -75.75226983587321,
            -75.76065618994208,
            -75.76018968336267,
            -75.7635480699164,
            -75.76390730372928,
            -75.76180071154775,
            -75.76259232553308,
            -75.76407393231719,
            -75.76420706358232,
            -75.76400825764863,
            -75.76395633690755,
            -75.76410968425144,
            -75.76391059177871,
            -75.76410052407006,
            -75.76401016727293,
            -75.76392148582441,
            -75.76392451343649,
            -75.7642436841943,
            -75.76398681192525,
            -75.76349045186141,
            -75.76445954762285,
            -75.76385848684542,
            -75.7635773913062,
            -75.76354245793819,
            -75.73715862202036,
            -75.76155719673571,
            -75.76589220067636,
            -75.76266736392292,
            -75.76452485438786,
            -75.76446137562395,
            -75.76534964806189,
            -75.76352706651527,
            -75.76488458987873,
            -75.76229663727246,
            -75.76296113163927,
            -75.7646540378359,
            -75.76415445156874,
            -75.76426892994597,
            -75.7631007284159,
            -75.7648356772403,
            -75.7641933406317,
            -75.76473359163404,
            -75.76464756675398,
            -75.76425454844849,
            -75.76425275440424,
            -75.7643353493438,
            -75.76429820908221,
            -75.76447373690898
        ],
        "e_xc": [
            -9.638984620620528,
            -8.915317409531028,
            -8.990070881698674,
            -9.052888445808103,
            -8.991035058688674,
            -9.01655852326137,
            -9.01031606852522,
            -9.003222675699266,
            -8.947571308743747,
            -8.993747325355468,
            -9.000563427896253,
            -8.992111213952704,
            -8.989932465189392,
            -8.999060261288339,
            -8.991296419343325,
            -8.99064943421393,
            -9.00339217633735,
            -8.99205347267748,
            -8.987788670030984,
            -9.023028722270231,
            -8.981336302353665,
            -8.930364724358153,
            -9.001735664595888,
            -8.970035890610772,
            -8.938582496552883,
            -8.938583232297766,
            -9.215923348565765,
            -8.931430334545905,
            -9.022554752988162,
            -9.000893858151715,
            -9.008059889611731,
            -9.029053434533008,
            -9.017412682407395,
            -9.039059221627205,
            -8.988762192959085,
            -9.018230170192531,
            -9.02671265240188,
            -9.027616838530644,
            -9.013090410634712,
            -9.019045995826042,
            -9.058403024824605,
            -9.01923921769454,
            -9.026941844328123,
            -9.0127110548241,
            -9.025309190058254,
            -9.029915657487068,
            -9.026934737853395,
            -9.002075493527947,
            -8.998718348635464,
            -9.005066962453677
        ],
        "iterations": 50
    },
    "scf_eigenvalues_a": {
        "dims": [
            5
        ],
        "size": 5,
        "vals": [
            -18.428550208953475,
            -0.38003253288785355,
            -0.24462934596811348,
            0.056615536004229305,
            0.056599290732569196
        ]
    },
    "time": "2024-05-03 21:57:58",
    "wall_time": 102.92303395271301
}